helloq/__init__.py
helloq/test_q.py
helloq-0.1.1.dist-info/licenses/LICENSE
helloq-0.1.1.dist-info/METADATA
helloq-0.1.1.dist-info/WHEEL
helloq-0.1.1.dist-info/top_level.txt
helloq-0.1.1.dist-info/RECORD
