Metadata-Version: 2.4
Name: helloq
Version: 0.1.1
Summary: Test uploading CI/CD to pypi -- delete soon
Requires-Python: >=3.12
License-File: LICENSE
Dynamic: license-file
